cli_mcp/__init__.py
cli_mcp/__main__.py
cli_mcp/config.py
cli_mcp/stdio.py
cli_mcp-0.18.0.dist-info/METADATA
cli_mcp-0.18.0.dist-info/WHEEL
cli_mcp-0.18.0.dist-info/entry_points.txt
cli_mcp-0.18.0.dist-info/top_level.txt
cli_mcp-0.18.0.dist-info/RECORD
