Metadata-Version: 2.4
Name: cli-mcp
Version: 0.18.0
Summary: Minimal MCP client CLI
Requires-Python: >=3.8
Requires-Dist: click
Requires-Dist: httpx
